{
  "parent": "tac_bingo:capture_mobs/row4/row4_col1_penguin",
  "display": {
    "icon": {
      "item": "portablemobs:master_capture_cell",
	  "nbt": "{has_entity: 1b, entity_type: \"alexsmobs:mantis_shrimp\"}"
    },
    "title": {
      "translate": "Capture a Mantis Shrimp"
    },
    "description": {
      "translate": "Not initially hostile, found in Warm Oceans or Mangrove Swamps"
    },
    "frame": "challenge",
    "show_toast": true,
    "announce_to_chat": true,
    "hidden": false
  },
  "criteria": {
    "capture_mob": {
      "trigger": "minecraft:player_interacted_with_entity",
      "conditions": {
        "item": {
          "items": [
            "portablemobs:basic_capture_cell",
            "portablemobs:master_capture_cell"
          ]
        },
        "entity": {
          "type": "alexsmobs:mantis_shrimp"
        }
      }
    }
  }
}